{"version":1,"resource":"vscode-remote://wsl%2Bubuntu/home/gaye/solution/login/index.html","entries":[{"id":"X6Ry.html","timestamp":1731911336349},{"id":"jzs7.html","timestamp":1731911477459},{"id":"O8MF.html","timestamp":1731911508859},{"id":"gkYp.html","timestamp":1731911636339},{"id":"kXUY.html","timestamp":1731912003369},{"id":"m2qc.html","timestamp":1731912088529},{"id":"oavM.html","timestamp":1731912835249},{"id":"VLdC.html","timestamp":1731913947229},{"id":"xZzM.html","timestamp":1731913962139}]}